solvency2sf/__init__.py
solvency2sf/aggregation.py
solvency2sf/corr_bscr.csv
solvency2sf/corr_h_slt.csv
solvency2sf/corr_h_uw.csv
solvency2sf/corr_mkt_down.csv
solvency2sf/corr_mkt_up.csv
solvency2sf/corr_nl_uw.csv
solvency2sf/default.py
solvency2sf/mkt.py
solvency2sf/operational.py
solvency2sf/mcr/__init__.py
solvency2sf/mcr/factors_mcr.csv
solvency2sf/mcr/mcr.py
solvency2sf/scr_h/__init__.py
solvency2sf/scr_h/slt/__init__.py
solvency2sf/scr_nl/__init__.py
solvency2sf/scr_nl/cat/__init__.py
solvency2sf/scr_nl/cat/manmade/__init__.py
solvency2sf/scr_nl/cat/manmade/corr_liab.csv
solvency2sf/scr_nl/cat/manmade/factors_liab.csv
solvency2sf/scr_nl/cat/manmade/manmade.py
solvency2sf/scr_nl/cat/manmade/other_nl.csv
solvency2sf/scr_nl/cat/natcat_eur/__init__.py
solvency2sf/scr_nl/cat/natcat_eur/factors.csv
solvency2sf/scr_nl/cat/natcat_eur/natcat_eur.py
solvency2sf/scr_nl/cat/natcat_eur/scenarios.csv
solvency2sf/scr_nl/cat/natcat_eur/simplification.csv
solvency2sf/scr_nl/cat/natcat_eur/specified_loss.csv
solvency2sf/scr_nl/cat/natcat_eur/corr/earthquake.csv
solvency2sf/scr_nl/cat/natcat_eur/corr/flood.csv
solvency2sf/scr_nl/cat/natcat_eur/corr/hail.csv
solvency2sf/scr_nl/cat/natcat_eur/corr/subsidence.csv
solvency2sf/scr_nl/cat/natcat_eur/corr/windstorm.csv
solvency2sf/scr_nl/cat/natcat_eur/corr_cresta/earthquake_AT.csv
solvency2sf/scr_nl/cat/natcat_eur/corr_cresta/earthquake_BE.csv
solvency2sf/scr_nl/cat/natcat_eur/corr_cresta/earthquake_BG.csv
solvency2sf/scr_nl/cat/natcat_eur/corr_cresta/earthquake_CH.csv
solvency2sf/scr_nl/cat/natcat_eur/corr_cresta/earthquake_CY.csv
solvency2sf/scr_nl/cat/natcat_eur/corr_cresta/earthquake_CZ.csv
solvency2sf/scr_nl/cat/natcat_eur/corr_cresta/earthquake_DE.csv
solvency2sf/scr_nl/cat/natcat_eur/corr_cresta/earthquake_FR.csv
solvency2sf/scr_nl/cat/natcat_eur/corr_cresta/earthquake_GR.csv
solvency2sf/scr_nl/cat/natcat_eur/corr_cresta/earthquake_HR.csv
solvency2sf/scr_nl/cat/natcat_eur/corr_cresta/earthquake_HU.csv
solvency2sf-0.0.35.dist-info/LICENSE
solvency2sf-0.0.35.dist-info/METADATA
solvency2sf-0.0.35.dist-info/WHEEL
solvency2sf-0.0.35.dist-info/top_level.txt
solvency2sf-0.0.35.dist-info/RECORD
