Metadata-Version: 2.1
Name: solvency2sf
Version: 0.0.35
Summary: Solvency 2 Standard Formula
Home-page: https://github.com/pdavidsonFIA/solvency2sf
Author: Peter Davidson
Author-email: peterjd41@gmail.com
Project-URL: Bug Tracker, https://github.com/pdavidsonFIA/solvency2sf/issues
Classifier: Programming Language :: Python :: 3
Classifier: License :: OSI Approved :: MIT License
Classifier: Operating System :: OS Independent
Classifier: Development Status :: 2 - Pre-Alpha
Classifier: Intended Audience :: Financial and Insurance Industry
Requires-Python: >=3.6
License-File: LICENSE
Requires-Dist: pandas (>=1.0.0)
